{
	"1001": {
		"File": "triceCheck.c",
		"Line": 879
	},
	"1004": {
		"File": "triceCheck.c",
		"Line": 858
	},
	"1015": {
		"File": "triceCheck.c",
		"Line": 446
	},
	"1023": {
		"File": "triceCheck.c",
		"Line": 548
	},
	"1027": {
		"File": "triceCheck.c",
		"Line": 1013
	},
	"1035": {
		"File": "triceCheck.c",
		"Line": 1247
	},
	"1043": {
		"File": "triceCheck.c",
		"Line": 433
	},
	"1045": {
		"File": "triceCheck.c",
		"Line": 1146
	},
	"1051": {
		"File": "triceCheck.c",
		"Line": 430
	},
	"1059": {
		"File": "triceCheck.c",
		"Line": 783
	},
	"1078": {
		"File": "triceCheck.c",
		"Line": 626
	},
	"1084": {
		"File": "triceCheck.c",
		"Line": 838
	},
	"1086": {
		"File": "triceCheck.c",
		"Line": 389
	},
	"1091": {
		"File": "triceCheck.c",
		"Line": 1536
	},
	"1099": {
		"File": "triceCheck.c",
		"Line": 460
	},
	"1101": {
		"File": "triceCheck.c",
		"Line": 1165
	},
	"1110": {
		"File": "triceCheck.c",
		"Line": 383
	},
	"1127": {
		"File": "triceCheck.c",
		"Line": 1081
	},
	"1135": {
		"File": "triceCheck.c",
		"Line": 566
	},
	"1142": {
		"File": "triceCheck.c",
		"Line": 489
	},
	"1159": {
		"File": "triceCheck.c",
		"Line": 264
	},
	"1168": {
		"File": "triceCheck.c",
		"Line": 1272
	},
	"1188": {
		"File": "triceCheck.c",
		"Line": 1315
	},
	"1190": {
		"File": "triceCheck.c",
		"Line": 845
	},
	"1207": {
		"File": "triceCheck.c",
		"Line": 1006
	},
	"1230": {
		"File": "triceCheck.c",
		"Line": 182
	},
	"1237": {
		"File": "triceCheck.c",
		"Line": 674
	},
	"1245": {
		"File": "triceCheck.c",
		"Line": 1076
	},
	"1257": {
		"File": "triceCheck.c",
		"Line": 881
	},
	"1270": {
		"File": "triceCheck.c",
		"Line": 1289
	},
	"1272": {
		"File": "triceCheck.c",
		"Line": 1177
	},
	"1278": {
		"File": "triceCheck.c",
		"Line": 864
	},
	"1286": {
		"File": "triceCheck.c",
		"Line": 917
	},
	"1288": {
		"File": "triceCheck.c",
		"Line": 288
	},
	"1291": {
		"File": "triceCheck.c",
		"Line": 911
	},
	"1298": {
		"File": "triceCheck.c",
		"Line": 1239
	},
	"1307": {
		"File": "triceCheck.c",
		"Line": 712
	},
	"1311": {
		"File": "triceCheck.c",
		"Line": 1299
	},
	"1314": {
		"File": "triceCheck.c",
		"Line": 586
	},
	"1316": {
		"File": "triceCheck.c",
		"Line": 1096
	},
	"1320": {
		"File": "triceCheck.c",
		"Line": 926
	},
	"1327": {
		"File": "main.c",
		"Line": 90
	},
	"1335": {
		"File": "triceCheck.c",
		"Line": 1186
	},
	"1338": {
		"File": "triceCheck.c",
		"Line": 813
	},
	"1349": {
		"File": "triceCheck.c",
		"Line": 588
	},
	"1354": {
		"File": "triceCheck.c",
		"Line": 551
	},
	"1367": {
		"File": "triceCheck.c",
		"Line": 1235
	},
	"1373": {
		"File": "triceCheck.c",
		"Line": 412
	},
	"1374": {
		"File": "triceCheck.c",
		"Line": 815
	},
	"1380": {
		"File": "triceCheck.c",
		"Line": 398
	},
	"1381": {
		"File": "triceCheck.c",
		"Line": 263
	},
	"1382": {
		"File": "triceCheck.c",
		"Line": 175
	},
	"1388": {
		"File": "triceCheck.c",
		"Line": 651
	},
	"1392": {
		"File": "triceCheck.c",
		"Line": 148
	},
	"1393": {
		"File": "triceCheck.c",
		"Line": 1011
	},
	"1396": {
		"File": "triceCheck.c",
		"Line": 188
	},
	"1398": {
		"File": "triceCheck.c",
		"Line": 683
	},
	"1403": {
		"File": "triceCheck.c",
		"Line": 713
	},
	"1414": {
		"File": "triceCheck.c",
		"Line": 1327
	},
	"1417": {
		"File": "triceCheck.c",
		"Line": 459
	},
	"1420": {
		"File": "triceCheck.c",
		"Line": 190
	},
	"1421": {
		"File": "triceCheck.c",
		"Line": 1004
	},
	"1429": {
		"File": "triceCheck.c",
		"Line": 1311
	},
	"1431": {
		"File": "triceCheck.c",
		"Line": 849
	},
	"1442": {
		"File": "triceCheck.c",
		"Line": 1164
	},
	"1452": {
		"File": "triceCheck.c",
		"Line": 659
	},
	"1453": {
		"File": "triceCheck.c",
		"Line": 741
	},
	"1455": {
		"File": "triceCheck.c",
		"Line": 667
	},
	"1457": {
		"File": "triceCheck.c",
		"Line": 1023
	},
	"1460": {
		"File": "triceCheck.c",
		"Line": 1020
	},
	"1462": {
		"File": "triceCheck.c",
		"Line": 522
	},
	"1464": {
		"File": "triceCheck.c",
		"Line": 200
	},
	"1471": {
		"File": "triceCheck.c",
		"Line": 1119
	},
	"1476": {
		"File": "triceCheck.c",
		"Line": 1246
	},
	"1478": {
		"File": "triceCheck.c",
		"Line": 422
	},
	"1481": {
		"File": "triceCheck.c",
		"Line": 953
	},
	"1489": {
		"File": "triceCheck.c",
		"Line": 163
	},
	"1490": {
		"File": "triceCheck.c",
		"Line": 1268
	},
	"1500": {
		"File": "triceCheck.c",
		"Line": 597
	},
	"1501": {
		"File": "triceCheck.c",
		"Line": 217
	},
	"1509": {
		"File": "triceCheck.c",
		"Line": 1340
	},
	"1515": {
		"File": "triceCheck.c",
		"Line": 799
	},
	"1523": {
		"File": "triceCheck.c",
		"Line": 973
	},
	"1524": {
		"File": "triceCheck.c",
		"Line": 581
	},
	"1525": {
		"File": "triceCheck.c",
		"Line": 270
	},
	"1527": {
		"File": "triceCheck.c",
		"Line": 889
	},
	"1532": {
		"File": "triceCheck.c",
		"Line": 1149
	},
	"1533": {
		"File": "triceCheck.c",
		"Line": 1493
	},
	"1554": {
		"File": "triceCheck.c",
		"Line": 393
	},
	"1562": {
		"File": "triceCheck.c",
		"Line": 510
	},
	"1572": {
		"File": "triceCheck.c",
		"Line": 1159
	},
	"1577": {
		"File": "triceCheck.c",
		"Line": 1083
	},
	"1586": {
		"File": "triceCheck.c",
		"Line": 195
	},
	"1589": {
		"File": "triceCheck.c",
		"Line": 876
	},
	"1590": {
		"File": "triceCheck.c",
		"Line": 710
	},
	"1608": {
		"File": "triceCheck.c",
		"Line": 254
	},
	"1611": {
		"File": "triceCheck.c",
		"Line": 358
	},
	"1619": {
		"File": "triceCheck.c",
		"Line": 822
	},
	"1620": {
		"File": "triceCheck.c",
		"Line": 1213
	},
	"1622": {
		"File": "triceCheck.c",
		"Line": 486
	},
	"1634": {
		"File": "triceCheck.c",
		"Line": 690
	},
	"1635": {
		"File": "triceCheck.c",
		"Line": 1015
	},
	"1644": {
		"File": "triceCheck.c",
		"Line": 733
	},
	"1645": {
		"File": "triceCheck.c",
		"Line": 387
	},
	"1649": {
		"File": "triceCheck.c",
		"Line": 1064
	},
	"1652": {
		"File": "triceCheck.c",
		"Line": 345
	},
	"1655": {
		"File": "triceCheck.c",
		"Line": 776
	},
	"1659": {
		"File": "triceCheck.c",
		"Line": 843
	},
	"1673": {
		"File": "triceCheck.c",
		"Line": 1484
	},
	"1677": {
		"File": "triceCheck.c",
		"Line": 432
	},
	"1689": {
		"File": "triceCheck.c",
		"Line": 801
	},
	"1690": {
		"File": "triceCheck.c",
		"Line": 269
	},
	"1691": {
		"File": "triceCheck.c",
		"Line": 1205
	},
	"1711": {
		"File": "triceCheck.c",
		"Line": 1178
	},
	"1712": {
		"File": "triceCheck.c",
		"Line": 508
	},
	"1721": {
		"File": "triceCheck.c",
		"Line": 394
	},
	"1726": {
		"File": "triceCheck.c",
		"Line": 785
	},
	"1731": {
		"File": "triceCheck.c",
		"Line": 549
	},
	"1732": {
		"File": "triceCheck.c",
		"Line": 957
	},
	"1733": {
		"File": "triceCheck.c",
		"Line": 462
	},
	"1734": {
		"File": "triceCheck.c",
		"Line": 603
	},
	"1738": {
		"File": "triceCheck.c",
		"Line": 54
	},
	"1744": {
		"File": "triceCheck.c",
		"Line": 375
	},
	"1749": {
		"File": "triceCheck.c",
		"Line": 1118
	},
	"1752": {
		"File": "triceCheck.c",
		"Line": 877
	},
	"1753": {
		"File": "triceCheck.c",
		"Line": 198
	},
	"1758": {
		"File": "triceCheck.c",
		"Line": 1171
	},
	"1762": {
		"File": "triceCheck.c",
		"Line": 620
	},
	"1768": {
		"File": "triceCheck.c",
		"Line": 134
	},
	"1772": {
		"File": "triceCheck.c",
		"Line": 1334
	},
	"1787": {
		"File": "triceCheck.c",
		"Line": 639
	},
	"1788": {
		"File": "triceCheck.c",
		"Line": 1222
	},
	"1791": {
		"File": "triceCheck.c",
		"Line": 1057
	},
	"1792": {
		"File": "triceCheck.c",
		"Line": 1316
	},
	"1797": {
		"File": "triceCheck.c",
		"Line": 1093
	},
	"1798": {
		"File": "triceCheck.c",
		"Line": 541
	},
	"1810": {
		"File": "triceCheck.c",
		"Line": 354
	},
	"1811": {
		"File": "triceCheck.c",
		"Line": 1290
	},
	"1820": {
		"File": "triceCheck.c",
		"Line": 670
	},
	"1829": {
		"File": "triceCheck.c",
		"Line": 806
	},
	"1836": {
		"File": "triceCheck.c",
		"Line": 220
	},
	"1842": {
		"File": "triceCheck.c",
		"Line": 368
	},
	"1853": {
		"File": "triceCheck.c",
		"Line": 176
	},
	"1855": {
		"File": "triceCheck.c",
		"Line": 738
	},
	"1859": {
		"File": "triceCheck.c",
		"Line": 1110
	},
	"1861": {
		"File": "triceCheck.c",
		"Line": 418
	},
	"1862": {
		"File": "triceCheck.c",
		"Line": 962
	},
	"1869": {
		"File": "triceCheck.c",
		"Line": 873
	},
	"1887": {
		"File": "triceCheck.c",
		"Line": 309
	},
	"1890": {
		"File": "triceCheck.c",
		"Line": 1140
	},
	"1914": {
		"File": "triceCheck.c",
		"Line": 563
	},
	"1920": {
		"File": "triceCheck.c",
		"Line": 984
	},
	"1923": {
		"File": "triceCheck.c",
		"Line": 267
	},
	"1925": {
		"File": "triceCheck.c",
		"Line": 664
	},
	"1933": {
		"File": "triceCheck.c",
		"Line": 742
	},
	"1934": {
		"File": "triceCheck.c",
		"Line": 1230
	},
	"1953": {
		"File": "triceCheck.c",
		"Line": 444
	},
	"1956": {
		"File": "triceCheck.c",
		"Line": 995
	},
	"1976": {
		"File": "triceCheck.c",
		"Line": 797
	},
	"1987": {
		"File": "triceCheck.c",
		"Line": 760
	},
	"1988": {
		"File": "triceCheck.c",
		"Line": 453
	},
	"2003": {
		"File": "triceCheck.c",
		"Line": 976
	},
	"2008": {
		"File": "triceCheck.c",
		"Line": 1291
	},
	"2014": {
		"File": "triceCheck.c",
		"Line": 987
	},
	"2015": {
		"File": "triceCheck.c",
		"Line": 480
	},
	"2028": {
		"File": "triceCheck.c",
		"Line": 575
	},
	"2042": {
		"File": "triceCheck.c",
		"Line": 1294
	},
	"2046": {
		"File": "triceCheck.c",
		"Line": 1123
	},
	"2049": {
		"File": "triceCheck.c",
		"Line": 900
	},
	"2053": {
		"File": "triceCheck.c",
		"Line": 523
	},
	"2059": {
		"File": "triceCheck.c",
		"Line": 618
	},
	"2066": {
		"File": "triceCheck.c",
		"Line": 1251
	},
	"2069": {
		"File": "triceCheck.c",
		"Line": 308
	},
	"2084": {
		"File": "triceCheck.c",
		"Line": 364
	},
	"2087": {
		"File": "triceCheck.c",
		"Line": 158
	},
	"2092": {
		"File": "triceCheck.c",
		"Line": 745
	},
	"2096": {
		"File": "triceCheck.c",
		"Line": 1197
	},
	"2106": {
		"File": "triceCheck.c",
		"Line": 1338
	},
	"2109": {
		"File": "triceCheck.c",
		"Line": 923
	},
	"2112": {
		"File": "triceCheck.c",
		"Line": 1138
	},
	"2119": {
		"File": "triceCheck.c",
		"Line": 1134
	},
	"2122": {
		"File": "triceCheck.c",
		"Line": 854
	},
	"2123": {
		"File": "triceCheck.c",
		"Line": 1059
	},
	"2127": {
		"File": "triceCheck.c",
		"Line": 526
	},
	"2159": {
		"File": "triceCheck.c",
		"Line": 577
	},
	"2175": {
		"File": "triceCheck.c",
		"Line": 696
	},
	"2179": {
		"File": "triceCheck.c",
		"Line": 513
	},
	"2187": {
		"File": "triceCheck.c",
		"Line": 892
	},
	"2190": {
		"File": "triceCheck.c",
		"Line": 829
	},
	"2191": {
		"File": "triceCheck.c",
		"Line": 820
	},
	"2221": {
		"File": "triceCheck.c",
		"Line": 440
	},
	"2243": {
		"File": "triceCheck.c",
		"Line": 370
	},
	"2245": {
		"File": "triceCheck.c",
		"Line": 1077
	},
	"2246": {
		"File": "triceCheck.c",
		"Line": 553
	},
	"2250": {
		"File": "triceCheck.c",
		"Line": 546
	},
	"2251": {
		"File": "triceCheck.c",
		"Line": 1207
	},
	"2262": {
		"File": "triceCheck.c",
		"Line": 743
	},
	"2264": {
		"File": "triceCheck.c",
		"Line": 941
	},
	"2280": {
		"File": "triceCheck.c",
		"Line": 748
	},
	"2290": {
		"File": "triceCheck.c",
		"Line": 761
	},
	"2304": {
		"File": "triceCheck.c",
		"Line": 133
	},
	"2322": {
		"File": "triceCheck.c",
		"Line": 245
	},
	"2335": {
		"File": "triceCheck.c",
		"Line": 1098
	},
	"2338": {
		"File": "triceCheck.c",
		"Line": 257
	},
	"2347": {
		"File": "triceCheck.c",
		"Line": 821
	},
	"2350": {
		"File": "triceCheck.c",
		"Line": 1298
	},
	"2359": {
		"File": "triceCheck.c",
		"Line": 590
	},
	"2365": {
		"File": "triceCheck.c",
		"Line": 954
	},
	"2368": {
		"File": "triceCheck.c",
		"Line": 928
	},
	"2372": {
		"File": "triceCheck.c",
		"Line": 376
	},
	"2377": {
		"File": "triceCheck.c",
		"Line": 609
	},
	"2389": {
		"File": "triceCheck.c",
		"Line": 1261
	},
	"2395": {
		"File": "triceCheck.c",
		"Line": 1083
	},
	"2403": {
		"File": "triceCheck.c",
		"Line": 1192
	},
	"2407": {
		"File": "triceCheck.c",
		"Line": 1019
	},
	"2418": {
		"File": "triceCheck.c",
		"Line": 695
	},
	"2427": {
		"File": "triceCheck.c",
		"Line": 268
	},
	"2431": {
		"File": "triceCheck.c",
		"Line": 170
	},
	"2442": {
		"File": "triceCheck.c",
		"Line": 734
	},
	"2444": {
		"File": "triceCheck.c",
		"Line": 1126
	},
	"2448": {
		"File": "triceCheck.c",
		"Line": 390
	},
	"2455": {
		"File": "triceCheck.c",
		"Line": 485
	},
	"2456": {
		"File": "triceCheck.c",
		"Line": 1212
	},
	"2458": {
		"File": "triceCheck.c",
		"Line": 1265
	},
	"2462": {
		"File": "triceCheck.c",
		"Line": 439
	},
	"2464": {
		"File": "triceCheck.c",
		"Line": 455
	},
	"2473": {
		"File": "triceCheck.c",
		"Line": 847
	},
	"2475": {
		"File": "triceCheck.c",
		"Line": 1150
	},
	"2496": {
		"File": "triceCheck.c",
		"Line": 506
	},
	"2502": {
		"File": "triceCheck.c",
		"Line": 963
	},
	"2514": {
		"File": "main.c",
		"Line": 91
	},
	"2539": {
		"File": "triceCheck.c",
		"Line": 1231
	},
	"2540": {
		"File": "triceCheck.c",
		"Line": 1099
	},
	"2546": {
		"File": "triceCheck.c",
		"Line": 1103
	},
	"2547": {
		"File": "triceCheck.c",
		"Line": 205
	},
	"2548": {
		"File": "triceCheck.c",
		"Line": 946
	},
	"2551": {
		"File": "triceCheck.c",
		"Line": 1107
	},
	"2558": {
		"File": "triceCheck.c",
		"Line": 224
	},
	"2568": {
		"File": "triceCheck.c",
		"Line": 1305
	},
	"2576": {
		"File": "triceCheck.c",
		"Line": 753
	},
	"2579": {
		"File": "triceCheck.c",
		"Line": 491
	},
	"2580": {
		"File": "triceCheck.c",
		"Line": 1209
	},
	"2581": {
		"File": "triceCheck.c",
		"Line": 259
	},
	"2584": {
		"File": "triceCheck.c",
		"Line": 1218
	},
	"2591": {
		"File": "triceCheck.c",
		"Line": 796
	},
	"2592": {
		"File": "triceCheck.c",
		"Line": 482
	},
	"2602": {
		"File": "triceCheck.c",
		"Line": 912
	},
	"2605": {
		"File": "triceCheck.c",
		"Line": 648
	},
	"2608": {
		"File": "triceCheck.c",
		"Line": 472
	},
	"2611": {
		"File": "triceCheck.c",
		"Line": 1297
	},
	"2615": {
		"File": "triceCheck.c",
		"Line": 470
	},
	"2617": {
		"File": "triceCheck.c",
		"Line": 883
	},
	"2626": {
		"File": "triceCheck.c",
		"Line": 1264
	},
	"2636": {
		"File": "triceCheck.c",
		"Line": 1514
	},
	"2640": {
		"File": "triceCheck.c",
		"Line": 569
	},
	"2645": {
		"File": "triceCheck.c",
		"Line": 179
	},
	"2647": {
		"File": "triceCheck.c",
		"Line": 1133
	},
	"2650": {
		"File": "triceCheck.c",
		"Line": 496
	},
	"2677": {
		"File": "triceCheck.c",
		"Line": 1018
	},
	"2681": {
		"File": "triceCheck.c",
		"Line": 895
	},
	"2688": {
		"File": "triceCheck.c",
		"Line": 863
	},
	"2695": {
		"File": "triceCheck.c",
		"Line": 1047
	},
	"2697": {
		"File": "triceCheck.c",
		"Line": 918
	},
	"2700": {
		"File": "main.c",
		"Line": 92
	},
	"2702": {
		"File": "triceCheck.c",
		"Line": 449
	},
	"2712": {
		"File": "triceCheck.c",
		"Line": 950
	},
	"2714": {
		"File": "triceCheck.c",
		"Line": 1101
	},
	"2717": {
		"File": "triceCheck.c",
		"Line": 616
	},
	"2729": {
		"File": "triceCheck.c",
		"Line": 544
	},
	"2733": {
		"File": "triceCheck.c",
		"Line": 1286
	},
	"2742": {
		"File": "triceCheck.c",
		"Line": 1325
	},
	"2744": {
		"File": "triceCheck.c",
		"Line": 138
	},
	"2745": {
		"File": "triceCheck.c",
		"Line": 436
	},
	"2747": {
		"File": "triceCheck.c",
		"Line": 630
	},
	"2751": {
		"File": "triceCheck.c",
		"Line": 688
	},
	"2753": {
		"File": "triceCheck.c",
		"Line": 807
	},
	"2771": {
		"File": "triceCheck.c",
		"Line": 768
	},
	"2789": {
		"File": "triceCheck.c",
		"Line": 1039
	},
	"2793": {
		"File": "triceCheck.c",
		"Line": 872
	},
	"2795": {
		"File": "triceCheck.c",
		"Line": 1216
	},
	"2797": {
		"File": "triceCheck.c",
		"Line": 1339
	},
	"2798": {
		"File": "triceCheck.c",
		"Line": 261
	},
	"2800": {
		"File": "triceCheck.c",
		"Line": 391
	},
	"2810": {
		"File": "triceCheck.c",
		"Line": 971
	},
	"2812": {
		"File": "triceCheck.c",
		"Line": 1167
	},
	"2827": {
		"File": "triceCheck.c",
		"Line": 595
	},
	"2831": {
		"File": "triceCheck.c",
		"Line": 1579
	},
	"2835": {
		"File": "triceCheck.c",
		"Line": 488
	},
	"2837": {
		"File": "triceCheck.c",
		"Line": 438
	},
	"2838": {
		"File": "triceCheck.c",
		"Line": 428
	},
	"2840": {
		"File": "triceCheck.c",
		"Line": 887
	},
	"2843": {
		"File": "triceCheck.c",
		"Line": 861
	},
	"2854": {
		"File": "triceCheck.c",
		"Line": 325
	},
	"2855": {
		"File": "triceCheck.c",
		"Line": 608
	},
	"2859": {
		"File": "triceCheck.c",
		"Line": 943
	},
	"2871": {
		"File": "triceCheck.c",
		"Line": 1283
	},
	"2877": {
		"File": "triceCheck.c",
		"Line": 906
	},
	"2878": {
		"File": "triceCheck.c",
		"Line": 1055
	},
	"2880": {
		"File": "triceCheck.c",
		"Line": 402
	},
	"2882": {
		"File": "triceCheck.c",
		"Line": 1201
	},
	"2883": {
		"File": "triceCheck.c",
		"Line": 817
	},
	"2898": {
		"File": "triceCheck.c",
		"Line": 378
	},
	"2900": {
		"File": "triceCheck.c",
		"Line": 574
	},
	"2926": {
		"File": "triceCheck.c",
		"Line": 1043
	},
	"2927": {
		"File": "triceCheck.c",
		"Line": 942
	},
	"2928": {
		"File": "triceCheck.c",
		"Line": 1038
	},
	"2936": {
		"File": "triceCheck.c",
		"Line": 1079
	},
	"2958": {
		"File": "triceCheck.c",
		"Line": 675
	},
	"2960": {
		"File": "triceCheck.c",
		"Line": 60
	},
	"2963": {
		"File": "triceCheck.c",
		"Line": 848
	},
	"2968": {
		"File": "triceCheck.c",
		"Line": 169
	},
	"2976": {
		"File": "triceCheck.c",
		"Line": 413
	},
	"2982": {
		"File": "triceCheck.c",
		"Line": 972
	},
	"2983": {
		"File": "triceCheck.c",
		"Line": 839
	},
	"2985": {
		"File": "triceCheck.c",
		"Line": 1054
	},
	"2992": {
		"File": "triceCheck.c",
		"Line": 324
	},
	"3021": {
		"File": "triceCheck.c",
		"Line": 686
	},
	"3023": {
		"File": "triceCheck.c",
		"Line": 791
	},
	"3048": {
		"File": "triceCheck.c",
		"Line": 1092
	},
	"3052": {
		"File": "triceCheck.c",
		"Line": 632
	},
	"3054": {
		"File": "triceCheck.c",
		"Line": 665
	},
	"3059": {
		"File": "triceCheck.c",
		"Line": 1202
	},
	"3065": {
		"File": "triceCheck.c",
		"Line": 601
	},
	"3067": {
		"File": "triceCheck.c",
		"Line": 1295
	},
	"3076": {
		"File": "triceCheck.c",
		"Line": 1163
	},
	"3087": {
		"File": "triceCheck.c",
		"Line": 183
	},
	"3090": {
		"File": "triceCheck.c",
		"Line": 823
	},
	"3091": {
		"File": "triceCheck.c",
		"Line": 970
	},
	"3110": {
		"File": "triceCheck.c",
		"Line": 915
	},
	"3116": {
		"File": "triceCheck.c",
		"Line": 629
	},
	"3127": {
		"File": "triceCheck.c",
		"Line": 678
	},
	"3139": {
		"File": "triceCheck.c",
		"Line": 956
	},
	"3154": {
		"File": "triceCheck.c",
		"Line": 226
	},
	"3166": {
		"File": "triceCheck.c",
		"Line": 1331
	},
	"3176": {
		"File": "triceCheck.c",
		"Line": 542
	},
	"3185": {
		"File": "triceCheck.c",
		"Line": 751
	},
	"3188": {
		"File": "triceCheck.c",
		"Line": 528
	},
	"3189": {
		"File": "triceCheck.c",
		"Line": 193
	},
	"3195": {
		"File": "triceCheck.c",
		"Line": 1066
	},
	"3203": {
		"File": "triceCheck.c",
		"Line": 1183
	},
	"3213": {
		"File": "triceCheck.c",
		"Line": 1301
	},
	"3214": {
		"File": "triceCheck.c",
		"Line": 657
	},
	"3225": {
		"File": "triceCheck.c",
		"Line": 178
	},
	"3226": {
		"File": "triceCheck.c",
		"Line": 758
	},
	"3227": {
		"File": "triceCheck.c",
		"Line": 464
	},
	"3229": {
		"File": "triceCheck.c",
		"Line": 420
	},
	"3232": {
		"File": "triceCheck.c",
		"Line": 494
	},
	"3234": {
		"File": "triceCheck.c",
		"Line": 697
	},
	"3246": {
		"File": "triceCheck.c",
		"Line": 271
	},
	"3248": {
		"File": "triceCheck.c",
		"Line": 605
	},
	"3250": {
		"File": "triceCheck.c",
		"Line": 147
	},
	"3252": {
		"File": "triceCheck.c",
		"Line": 996
	},
	"3259": {
		"File": "triceCheck.c",
		"Line": 771
	},
	"3260": {
		"File": "triceCheck.c",
		"Line": 1161
	},
	"3263": {
		"File": "triceCheck.c",
		"Line": 625
	},
	"3269": {
		"File": "triceCheck.c",
		"Line": 550
	},
	"3275": {
		"File": "triceCheck.c",
		"Line": 615
	},
	"3286": {
		"File": "triceCheck.c",
		"Line": 177
	},
	"3297": {
		"File": "triceCheck.c",
		"Line": 1148
	},
	"3300": {
		"File": "triceCheck.c",
		"Line": 1069
	},
	"3303": {
		"File": "triceCheck.c",
		"Line": 811
	},
	"3307": {
		"File": "triceCheck.c",
		"Line": 556
	},
	"3312": {
		"File": "triceCheck.c",
		"Line": 1278
	},
	"3314": {
		"File": "triceCheck.c",
		"Line": 1267
	},
	"3318": {
		"File": "triceCheck.c",
		"Line": 1220
	},
	"3322": {
		"File": "triceCheck.c",
		"Line": 1227
	},
	"3326": {
		"File": "triceCheck.c",
		"Line": 589
	},
	"3327": {
		"File": "triceCheck.c",
		"Line": 1193
	},
	"3328": {
		"File": "triceCheck.c",
		"Line": 826
	},
	"3340": {
		"File": "triceCheck.c",
		"Line": 960
	},
	"3350": {
		"File": "triceCheck.c",
		"Line": 452
	},
	"3362": {
		"File": "triceCheck.c",
		"Line": 386
	},
	"3364": {
		"File": "triceCheck.c",
		"Line": 1287
	},
	"3375": {
		"File": "triceCheck.c",
		"Line": 1112
	},
	"3387": {
		"File": "triceCheck.c",
		"Line": 1271
	},
	"3391": {
		"File": "triceCheck.c",
		"Line": 535
	},
	"3392": {
		"File": "triceCheck.c",
		"Line": 1574
	},
	"3399": {
		"File": "triceCheck.c",
		"Line": 841
	},
	"3402": {
		"File": "triceCheck.c",
		"Line": 570
	},
	"3413": {
		"File": "triceCheck.c",
		"Line": 157
	},
	"3417": {
		"File": "triceCheck.c",
		"Line": 281
	},
	"3433": {
		"File": "triceCheck.c",
		"Line": 1129
	},
	"3443": {
		"File": "triceCheck.c",
		"Line": 1269
	},
	"3447": {
		"File": "triceCheck.c",
		"Line": 808
	},
	"3452": {
		"File": "triceCheck.c",
		"Line": 756
	},
	"3472": {
		"File": "triceCheck.c",
		"Line": 855
	},
	"3479": {
		"File": "triceCheck.c",
		"Line": 161
	},
	"3481": {
		"File": "triceCheck.c",
		"Line": 784
	},
	"3487": {
		"File": "triceCheck.c",
		"Line": 1072
	},
	"3491": {
		"File": "stm32l4xx_it.c",
		"Line": 200
	},
	"3497": {
		"File": "triceCheck.c",
		"Line": 754
	},
	"3502": {
		"File": "triceCheck.c",
		"Line": 1266
	},
	"3506": {
		"File": "triceCheck.c",
		"Line": 587
	},
	"3509": {
		"File": "triceCheck.c",
		"Line": 1302
	},
	"3517": {
		"File": "triceCheck.c",
		"Line": 450
	},
	"3520": {
		"File": "triceCheck.c",
		"Line": 289
	},
	"3522": {
		"File": "triceCheck.c",
		"Line": 1561
	},
	"3529": {
		"File": "triceCheck.c",
		"Line": 623
	},
	"3535": {
		"File": "triceCheck.c",
		"Line": 1234
	},
	"3539": {
		"File": "triceCheck.c",
		"Line": 437
	},
	"3549": {
		"File": "triceCheck.c",
		"Line": 1124
	},
	"3550": {
		"File": "triceCheck.c",
		"Line": 1243
	},
	"3552": {
		"File": "triceCheck.c",
		"Line": 711
	},
	"3554": {
		"File": "triceCheck.c",
		"Line": 614
	},
	"3567": {
		"File": "triceCheck.c",
		"Line": 514
	},
	"3572": {
		"File": "triceCheck.c",
		"Line": 1180
	},
	"3574": {
		"File": "triceCheck.c",
		"Line": 1027
	},
	"3575": {
		"File": "triceCheck.c",
		"Line": 947
	},
	"3580": {
		"File": "triceCheck.c",
		"Line": 628
	},
	"3582": {
		"File": "triceCheck.c",
		"Line": 658
	},
	"3584": {
		"File": "triceCheck.c",
		"Line": 350
	},
	"3597": {
		"File": "triceCheck.c",
		"Line": 578
	},
	"3599": {
		"File": "triceCheck.c",
		"Line": 156
	},
	"3612": {
		"File": "triceCheck.c",
		"Line": 417
	},
	"3628": {
		"File": "triceCheck.c",
		"Line": 720
	},
	"3629": {
		"File": "triceCheck.c",
		"Line": 1485
	},
	"3632": {
		"File": "triceCheck.c",
		"Line": 1012
	},
	"3638": {
		"File": "triceCheck.c",
		"Line": 434
	},
	"3641": {
		"File": "triceCheck.c",
		"Line": 377
	},
	"3651": {
		"File": "triceCheck.c",
		"Line": 1273
	},
	"3652": {
		"File": "triceCheck.c",
		"Line": 699
	},
	"3661": {
		"File": "triceCheck.c",
		"Line": 1105
	},
	"3663": {
		"File": "triceCheck.c",
		"Line": 837
	},
	"3666": {
		"File": "triceCheck.c",
		"Line": 1068
	},
	"3669": {
		"File": "triceCheck.c",
		"Line": 707
	},
	"3672": {
		"File": "triceCheck.c",
		"Line": 1002
	},
	"3681": {
		"File": "triceCheck.c",
		"Line": 1111
	},
	"3689": {
		"File": "triceCheck.c",
		"Line": 355
	},
	"3693": {
		"File": "triceCheck.c",
		"Line": 498
	},
	"3699": {
		"File": "triceCheck.c",
		"Line": 1369
	},
	"3710": {
		"File": "triceCheck.c",
		"Line": 920
	},
	"3718": {
		"File": "triceCheck.c",
		"Line": 1033
	},
	"3720": {
		"File": "triceCheck.c",
		"Line": 824
	},
	"3724": {
		"File": "triceCheck.c",
		"Line": 225
	},
	"3729": {
		"File": "triceCheck.c",
		"Line": 1280
	},
	"3735": {
		"File": "triceCheck.c",
		"Line": 1199
	},
	"3737": {
		"File": "triceCheck.c",
		"Line": 1088
	},
	"3745": {
		"File": "triceCheck.c",
		"Line": 660
	},
	"3746": {
		"File": "triceCheck.c",
		"Line": 932
	},
	"3753": {
		"File": "triceCheck.c",
		"Line": 1082
	},
	"3754": {
		"File": "triceCheck.c",
		"Line": 283
	},
	"3759": {
		"File": "triceCheck.c",
		"Line": 474
	},
	"3765": {
		"File": "triceCheck.c",
		"Line": 1095
	},
	"3768": {
		"File": "triceCheck.c",
		"Line": 538
	},
	"3769": {
		"File": "triceCheck.c",
		"Line": 166
	},
	"3773": {
		"File": "triceCheck.c",
		"Line": 1324
	},
	"3777": {
		"File": "triceCheck.c",
		"Line": 689
	},
	"3779": {
		"File": "triceCheck.c",
		"Line": 579
	},
	"3781": {
		"File": "triceCheck.c",
		"Line": 448
	},
	"3783": {
		"File": "triceCheck.c",
		"Line": 1089
	},
	"3789": {
		"File": "triceCheck.c",
		"Line": 1029
	},
	"3793": {
		"File": "triceCheck.c",
		"Line": 540
	},
	"3795": {
		"File": "triceCheck.c",
		"Line": 924
	},
	"3804": {
		"File": "triceCheck.c",
		"Line": 809
	},
	"3811": {
		"File": "triceCheck.c",
		"Line": 1050
	},
	"3812": {
		"File": "triceCheck.c",
		"Line": 1292
	},
	"3820": {
		"File": "triceCheck.c",
		"Line": 1053
	},
	"3822": {
		"File": "triceCheck.c",
		"Line": 694
	},
	"3835": {
		"File": "main.c",
		"Line": 363
	},
	"3838": {
		"File": "triceCheck.c",
		"Line": 612
	},
	"3842": {
		"File": "triceCheck.c",
		"Line": 1215
	},
	"3846": {
		"File": "triceCheck.c",
		"Line": 921
	},
	"3855": {
		"File": "triceCheck.c",
		"Line": 1330
	},
	"3857": {
		"File": "triceCheck.c",
		"Line": 816
	},
	"3861": {
		"File": "triceCheck.c",
		"Line": 1572
	},
	"3863": {
		"File": "triceCheck.c",
		"Line": 1486
	},
	"3864": {
		"File": "triceCheck.c",
		"Line": 723
	},
	"3873": {
		"File": "triceCheck.c",
		"Line": 1194
	},
	"3890": {
		"File": "triceCheck.c",
		"Line": 1191
	},
	"3891": {
		"File": "triceCheck.c",
		"Line": 945
	},
	"3896": {
		"File": "triceCheck.c",
		"Line": 789
	},
	"3899": {
		"File": "triceCheck.c",
		"Line": 492
	},
	"3900": {
		"File": "triceCheck.c",
		"Line": 914
	},
	"3902": {
		"File": "triceCheck.c",
		"Line": 227
	},
	"3905": {
		"File": "triceCheck.c",
		"Line": 431
	},
	"3918": {
		"File": "triceCheck.c",
		"Line": 371
	},
	"3924": {
		"File": "triceCheck.c",
		"Line": 894
	},
	"3965": {
		"File": "triceCheck.c",
		"Line": 732
	},
	"3966": {
		"File": "triceCheck.c",
		"Line": 1157
	},
	"3976": {
		"File": "triceCheck.c",
		"Line": 604
	},
	"3977": {
		"File": "triceCheck.c",
		"Line": 1515
	},
	"3985": {
		"File": "triceCheck.c",
		"Line": 907
	},
	"3987": {
		"File": "triceCheck.c",
		"Line": 927
	},
	"3990": {
		"File": "triceCheck.c",
		"Line": 1115
	},
	"3996": {
		"File": "triceCheck.c",
		"Line": 153
	},
	"3998": {
		"File": "triceCheck.c",
		"Line": 277
	},
	"4013": {
		"File": "triceCheck.c",
		"Line": 154
	},
	"4019": {
		"File": "triceCheck.c",
		"Line": 1495
	},
	"4023": {
		"File": "triceCheck.c",
		"Line": 463
	},
	"4025": {
		"File": "triceCheck.c",
		"Line": 1024
	},
	"4026": {
		"File": "triceCheck.c",
		"Line": 989
	},
	"4031": {
		"File": "triceCheck.c",
		"Line": 279
	},
	"4046": {
		"File": "triceCheck.c",
		"Line": 136
	},
	"4059": {
		"File": "triceCheck.c",
		"Line": 429
	},
	"4065": {
		"File": "triceCheck.c",
		"Line": 223
	},
	"4076": {
		"File": "triceCheck.c",
		"Line": 1040
	},
	"4085": {
		"File": "triceCheck.c",
		"Line": 866
	},
	"4087": {
		"File": "triceCheck.c",
		"Line": 559
	},
	"4091": {
		"File": "triceCheck.c",
		"Line": 493
	},
	"4098": {
		"File": "triceCheck.c",
		"Line": 633
	},
	"4112": {
		"File": "triceCheck.c",
		"Line": 948
	},
	"4113": {
		"File": "triceCheck.c",
		"Line": 635
	},
	"4114": {
		"File": "triceCheck.c",
		"Line": 1322
	},
	"4116": {
		"File": "triceCheck.c",
		"Line": 913
	},
	"4126": {
		"File": "triceCheck.c",
		"Line": 1248
	},
	"4128": {
		"File": "triceCheck.c",
		"Line": 644
	},
	"4135": {
		"File": "triceCheck.c",
		"Line": 865
	},
	"4137": {
		"File": "triceCheck.c",
		"Line": 580
	},
	"4143": {
		"File": "triceCheck.c",
		"Line": 878
	},
	"4147": {
		"File": "triceCheck.c",
		"Line": 919
	},
	"4148": {
		"File": "triceCheck.c",
		"Line": 1581
	},
	"4155": {
		"File": "triceCheck.c",
		"Line": 484
	},
	"4164": {
		"File": "triceCheck.c",
		"Line": 1139
	},
	"4172": {
		"File": "triceCheck.c",
		"Line": 1175
	},
	"4182": {
		"File": "triceCheck.c",
		"Line": 1255
	},
	"4183": {
		"File": "triceCheck.c",
		"Line": 617
	},
	"4198": {
		"File": "triceCheck.c",
		"Line": 1206
	},
	"4204": {
		"File": "triceCheck.c",
		"Line": 600
	},
	"4210": {
		"File": "triceCheck.c",
		"Line": 652
	},
	"4219": {
		"File": "triceCheck.c",
		"Line": 1481
	},
	"4221": {
		"File": "triceCheck.c",
		"Line": 746
	},
	"4223": {
		"File": "triceCheck.c",
		"Line": 500
	},
	"4225": {
		"File": "triceCheck.c",
		"Line": 1245
	},
	"4227": {
		"File": "triceCheck.c",
		"Line": 951
	},
	"4233": {
		"File": "triceCheck.c",
		"Line": 1224
	},
	"4238": {
		"File": "triceCheck.c",
		"Line": 208
	},
	"4240": {
		"File": "triceCheck.c",
		"Line": 1168
	},
	"4241": {
		"File": "triceCheck.c",
		"Line": 1528
	},
	"4258": {
		"File": "triceCheck.c",
		"Line": 416
	},
	"4264": {
		"File": "triceCheck.c",
		"Line": 1306
	},
	"4269": {
		"File": "triceCheck.c",
		"Line": 1155
	},
	"4292": {
		"File": "triceCheck.c",
		"Line": 1005
	},
	"4295": {
		"File": "triceCheck.c",
		"Line": 408
	},
	"4309": {
		"File": "triceCheck.c",
		"Line": 1223
	},
	"4323": {
		"File": "triceCheck.c",
		"Line": 893
	},
	"4324": {
		"File": "triceCheck.c",
		"Line": 594
	},
	"4330": {
		"File": "triceCheck.c",
		"Line": 1318
	},
	"4331": {
		"File": "triceCheck.c",
		"Line": 1065
	},
	"4346": {
		"File": "triceCheck.c",
		"Line": 840
	},
	"4363": {
		"File": "triceCheck.c",
		"Line": 875
	},
	"4373": {
		"File": "triceCheck.c",
		"Line": 573
	},
	"4390": {
		"File": "triceCheck.c",
		"Line": 1016
	},
	"4391": {
		"File": "triceCheck.c",
		"Line": 994
	},
	"4404": {
		"File": "triceCheck.c",
		"Line": 661
	},
	"4421": {
		"File": "triceCheck.c",
		"Line": 833
	},
	"4431": {
		"File": "triceCheck.c",
		"Line": 1300
	},
	"4433": {
		"File": "triceCheck.c",
		"Line": 966
	},
	"4437": {
		"File": "triceCheck.c",
		"Line": 367
	},
	"4439": {
		"File": "triceCheck.c",
		"Line": 938
	},
	"4450": {
		"File": "triceCheck.c",
		"Line": 599
	},
	"4451": {
		"File": "triceCheck.c",
		"Line": 1036
	},
	"4454": {
		"File": "triceCheck.c",
		"Line": 516
	},
	"4455": {
		"File": "triceCheck.c",
		"Line": 476
	},
	"4459": {
		"File": "triceCheck.c",
		"Line": 1317
	},
	"4471": {
		"File": "triceCheck.c",
		"Line": 1025
	},
	"4475": {
		"File": "triceCheck.c",
		"Line": 949
	},
	"4476": {
		"File": "triceCheck.c",
		"Line": 798
	},
	"4484": {
		"File": "triceCheck.c",
		"Line": 828
	},
	"4487": {
		"File": "triceCheck.c",
		"Line": 842
	},
	"4503": {
		"File": "triceCheck.c",
		"Line": 679
	},
	"4507": {
		"File": "triceCheck.c",
		"Line": 1284
	},
	"4519": {
		"File": "triceCheck.c",
		"Line": 638
	},
	"4528": {
		"File": "triceCheck.c",
		"Line": 908
	},
	"4529": {
		"File": "triceCheck.c",
		"Line": 704
	},
	"4534": {
		"File": "triceCheck.c",
		"Line": 1480
	},
	"4538": {
		"File": "triceCheck.c",
		"Line": 1127
	},
	"4543": {
		"File": "triceCheck.c",
		"Line": 1225
	},
	"4547": {
		"File": "triceCheck.c",
		"Line": 1008
	},
	"4552": {
		"File": "triceCheck.c",
		"Line": 501
	},
	"4553": {
		"File": "triceCheck.c",
		"Line": 836
	},
	"4556": {
		"File": "triceCheck.c",
		"Line": 997
	},
	"4557": {
		"File": "triceCheck.c",
		"Line": 348
	},
	"4560": {
		"File": "triceCheck.c",
		"Line": 487
	},
	"4563": {
		"File": "triceCheck.c",
		"Line": 1321
	},
	"4567": {
		"File": "triceCheck.c",
		"Line": 415
	},
	"4571": {
		"File": "triceCheck.c",
		"Line": 278
	},
	"4578": {
		"File": "triceCheck.c",
		"Line": 812
	},
	"4581": {
		"File": "triceCheck.c",
		"Line": 1169
	},
	"4600": {
		"File": "triceCheck.c",
		"Line": 1293
	},
	"4602": {
		"File": "triceCheck.c",
		"Line": 232
	},
	"4609": {
		"File": "triceCheck.c",
		"Line": 1010
	},
	"4612": {
		"File": "triceCheck.c",
		"Line": 1195
	},
	"4619": {
		"File": "triceCheck.c",
		"Line": 543
	},
	"4621": {
		"File": "triceCheck.c",
		"Line": 1343
	},
	"4623": {
		"File": "triceCheck.c",
		"Line": 777
	},
	"4632": {
		"File": "triceCheck.c",
		"Line": 1073
	},
	"4642": {
		"File": "triceCheck.c",
		"Line": 897
	},
	"4648": {
		"File": "triceCheck.c",
		"Line": 521
	},
	"4654": {
		"File": "triceCheck.c",
		"Line": 1237
	},
	"4667": {
		"File": "triceCheck.c",
		"Line": 1037
	},
	"4674": {
		"File": "triceCheck.c",
		"Line": 567
	},
	"4702": {
		"File": "triceCheck.c",
		"Line": 565
	},
	"4703": {
		"File": "triceCheck.c",
		"Line": 534
	},
	"4711": {
		"File": "triceCheck.c",
		"Line": 1184
	},
	"4716": {
		"File": "triceCheck.c",
		"Line": 152
	},
	"4720": {
		"File": "triceCheck.c",
		"Line": 1307
	},
	"4730": {
		"File": "triceCheck.c",
		"Line": 502
	},
	"4738": {
		"File": "triceCheck.c",
		"Line": 359
	},
	"4740": {
		"File": "triceCheck.c",
		"Line": 1277
	},
	"4743": {
		"File": "triceCheck.c",
		"Line": 668
	},
	"4744": {
		"File": "triceCheck.c",
		"Line": 1276
	},
	"4777": {
		"File": "triceCheck.c",
		"Line": 1137
	},
	"4795": {
		"File": "triceCheck.c",
		"Line": 955
	},
	"4796": {
		"File": "triceCheck.c",
		"Line": 228
	},
	"4812": {
		"File": "triceCheck.c",
		"Line": 509
	},
	"4830": {
		"File": "triceCheck.c",
		"Line": 979
	},
	"4838": {
		"File": "triceCheck.c",
		"Line": 1200
	},
	"4845": {
		"File": "triceCheck.c",
		"Line": 140
	},
	"4847": {
		"File": "triceCheck.c",
		"Line": 231
	},
	"4848": {
		"File": "triceCheck.c",
		"Line": 274
	},
	"4853": {
		"File": "triceCheck.c",
		"Line": 201
	},
	"4857": {
		"File": "triceCheck.c",
		"Line": 409
	},
	"4864": {
		"File": "triceCheck.c",
		"Line": 898
	},
	"4872": {
		"File": "triceCheck.c",
		"Line": 1082
	},
	"4876": {
		"File": "triceCheck.c",
		"Line": 419
	},
	"4881": {
		"File": "triceCheck.c",
		"Line": 554
	},
	"4882": {
		"File": "triceCheck.c",
		"Line": 1326
	},
	"4886": {
		"File": "triceCheck.c",
		"Line": 180
	},
	"4908": {
		"File": "triceCheck.c",
		"Line": 552
	},
	"4910": {
		"File": "triceCheck.c",
		"Line": 1366
	},
	"4914": {
		"File": "triceCheck.c",
		"Line": 905
	},
	"4922": {
		"File": "triceCheck.c",
		"Line": 621
	},
	"4926": {
		"File": "triceCheck.c",
		"Line": 852
	},
	"4934": {
		"File": "triceCheck.c",
		"Line": 192
	},
	"4945": {
		"File": "triceCheck.c",
		"Line": 929
	},
	"4953": {
		"File": "triceCheck.c",
		"Line": 610
	},
	"4967": {
		"File": "triceCheck.c",
		"Line": 1000
	},
	"4968": {
		"File": "triceCheck.c",
		"Line": 1162
	},
	"4969": {
		"File": "triceCheck.c",
		"Line": 1031
	},
	"4972": {
		"File": "triceCheck.c",
		"Line": 717
	},
	"4985": {
		"File": "triceCheck.c",
		"Line": 792
	},
	"5003": {
		"File": "triceCheck.c",
		"Line": 619
	},
	"5005": {
		"File": "triceCheck.c",
		"Line": 978
	},
	"5009": {
		"File": "triceCheck.c",
		"Line": 596
	},
	"5011": {
		"File": "triceCheck.c",
		"Line": 988
	},
	"5013": {
		"File": "triceCheck.c",
		"Line": 726
	},
	"5025": {
		"File": "triceCheck.c",
		"Line": 1166
	},
	"5040": {
		"File": "triceCheck.c",
		"Line": 1172
	},
	"5046": {
		"File": "triceCheck.c",
		"Line": 1256
	},
	"5050": {
		"File": "triceCheck.c",
		"Line": 149
	},
	"5053": {
		"File": "triceCheck.c",
		"Line": 869
	},
	"5054": {
		"File": "triceCheck.c",
		"Line": 1056
	},
	"5059": {
		"File": "triceCheck.c",
		"Line": 1312
	},
	"5066": {
		"File": "triceCheck.c",
		"Line": 380
	},
	"5078": {
		"File": "triceCheck.c",
		"Line": 682
	},
	"5087": {
		"File": "triceCheck.c",
		"Line": 1091
	},
	"5088": {
		"File": "triceCheck.c",
		"Line": 197
	},
	"5091": {
		"File": "triceCheck.c",
		"Line": 698
	},
	"5092": {
		"File": "triceCheck.c",
		"Line": 265
	},
	"5106": {
		"File": "triceCheck.c",
		"Line": 885
	},
	"5107": {
		"File": "triceCheck.c",
		"Line": 896
	},
	"5122": {
		"File": "triceCheck.c",
		"Line": 1045
	},
	"5128": {
		"File": "triceCheck.c",
		"Line": 222
	},
	"5144": {
		"File": "triceCheck.c",
		"Line": 1258
	},
	"5145": {
		"File": "triceCheck.c",
		"Line": 392
	},
	"5148": {
		"File": "triceCheck.c",
		"Line": 1028
	},
	"5152": {
		"File": "triceCheck.c",
		"Line": 1032
	},
	"5157": {
		"File": "triceCheck.c",
		"Line": 533
	},
	"5158": {
		"File": "triceCheck.c",
		"Line": 1253
	},
	"5169": {
		"File": "triceCheck.c",
		"Line": 774
	},
	"5172": {
		"File": "triceCheck.c",
		"Line": 1121
	},
	"5185": {
		"File": "triceCheck.c",
		"Line": 1262
	},
	"5190": {
		"File": "triceCheck.c",
		"Line": 384
	},
	"5192": {
		"File": "triceCheck.c",
		"Line": 172
	},
	"5199": {
		"File": "triceCheck.c",
		"Line": 297
	},
	"5201": {
		"File": "triceCheck.c",
		"Line": 1219
	},
	"5208": {
		"File": "triceCheck.c",
		"Line": 423
	},
	"5225": {
		"File": "triceCheck.c",
		"Line": 1048
	},
	"5242": {
		"File": "triceCheck.c",
		"Line": 189
	},
	"5246": {
		"File": "triceCheck.c",
		"Line": 1130
	},
	"5249": {
		"File": "triceCheck.c",
		"Line": 727
	},
	"5250": {
		"File": "triceCheck.c",
		"Line": 775
	},
	"5251": {
		"File": "triceCheck.c",
		"Line": 583
	},
	"5254": {
		"File": "triceCheck.c",
		"Line": 1335
	},
	"5265": {
		"File": "triceCheck.c",
		"Line": 490
	},
	"5266": {
		"File": "triceCheck.c",
		"Line": 356
	},
	"5271": {
		"File": "triceCheck.c",
		"Line": 1082
	},
	"5274": {
		"File": "triceCheck.c",
		"Line": 1242
	},
	"5286": {
		"File": "triceCheck.c",
		"Line": 1332
	},
	"5289": {
		"File": "triceCheck.c",
		"Line": 835
	},
	"5302": {
		"File": "triceCheck.c",
		"Line": 769
	},
	"5303": {
		"File": "triceCheck.c",
		"Line": 903
	},
	"5304": {
		"File": "triceCheck.c",
		"Line": 1257
	},
	"5308": {
		"File": "triceCheck.c",
		"Line": 786
	},
	"5309": {
		"File": "triceCheck.c",
		"Line": 1078
	},
	"5314": {
		"File": "triceCheck.c",
		"Line": 505
	},
	"5316": {
		"File": "triceCheck.c",
		"Line": 762
	},
	"5319": {
		"File": "triceCheck.c",
		"Line": 557
	},
	"5328": {
		"File": "triceCheck.c",
		"Line": 272
	},
	"5333": {
		"File": "triceCheck.c",
		"Line": 1060
	},
	"5336": {
		"File": "triceCheck.c",
		"Line": 53
	},
	"5343": {
		"File": "triceCheck.c",
		"Line": 1279
	},
	"5346": {
		"File": "triceCheck.c",
		"Line": 716
	},
	"5353": {
		"File": "triceCheck.c",
		"Line": 1154
	},
	"5367": {
		"File": "triceCheck.c",
		"Line": 443
	},
	"5368": {
		"File": "triceCheck.c",
		"Line": 1282
	},
	"5369": {
		"File": "triceCheck.c",
		"Line": 653
	},
	"5375": {
		"File": "triceCheck.c",
		"Line": 238
	},
	"5381": {
		"File": "triceCheck.c",
		"Line": 787
	},
	"5386": {
		"File": "triceCheck.c",
		"Line": 1017
	},
	"5394": {
		"File": "triceCheck.c",
		"Line": 1270
	},
	"5396": {
		"File": "triceCheck.c",
		"Line": 400
	},
	"5401": {
		"File": "triceCheck.c",
		"Line": 627
	},
	"5402": {
		"File": "triceCheck.c",
		"Line": 766
	},
	"5406": {
		"File": "triceCheck.c",
		"Line": 481
	},
	"5411": {
		"File": "triceCheck.c",
		"Line": 636
	},
	"5414": {
		"File": "triceCheck.c",
		"Line": 1075
	},
	"5431": {
		"File": "triceCheck.c",
		"Line": 560
	},
	"5439": {
		"File": "triceCheck.c",
		"Line": 352
	},
	"5443": {
		"File": "triceCheck.c",
		"Line": 1342
	},
	"5444": {
		"File": "triceCheck.c",
		"Line": 167
	},
	"5448": {
		"File": "triceCheck.c",
		"Line": 1275
	},
	"5470": {
		"File": "triceCheck.c",
		"Line": 139
	},
	"5472": {
		"File": "triceCheck.c",
		"Line": 1241
	},
	"5474": {
		"File": "triceCheck.c",
		"Line": 1080
	},
	"5477": {
		"File": "triceCheck.c",
		"Line": 202
	},
	"5479": {
		"File": "triceCheck.c",
		"Line": 346
	},
	"5483": {
		"File": "triceCheck.c",
		"Line": 1143
	},
	"5490": {
		"File": "triceCheck.c",
		"Line": 886
	},
	"5495": {
		"File": "triceCheck.c",
		"Line": 729
	},
	"5499": {
		"File": "triceCheck.c",
		"Line": 788
	},
	"5500": {
		"File": "triceCheck.c",
		"Line": 427
	},
	"5517": {
		"File": "triceCheck.c",
		"Line": 250
	},
	"5522": {
		"File": "triceCheck.c",
		"Line": 1546
	},
	"5526": {
		"File": "triceCheck.c",
		"Line": 229
	},
	"5528": {
		"File": "triceCheck.c",
		"Line": 1281
	},
	"5529": {
		"File": "triceCheck.c",
		"Line": 199
	},
	"5530": {
		"File": "triceCheck.c",
		"Line": 323
	},
	"5544": {
		"File": "triceCheck.c",
		"Line": 561
	},
	"5549": {
		"File": "triceCheck.c",
		"Line": 1583
	},
	"5559": {
		"File": "triceCheck.c",
		"Line": 353
	},
	"5568": {
		"File": "triceCheck.c",
		"Line": 203
	},
	"5570": {
		"File": "triceCheck.c",
		"Line": 296
	},
	"5574": {
		"File": "triceCheck.c",
		"Line": 844
	},
	"5587": {
		"File": "triceCheck.c",
		"Line": 702
	},
	"5600": {
		"File": "triceCheck.c",
		"Line": 968
	},
	"5606": {
		"File": "triceCheck.c",
		"Line": 555
	},
	"5614": {
		"File": "triceCheck.c",
		"Line": 1497
	},
	"5615": {
		"File": "triceCheck.c",
		"Line": 1160
	},
	"5626": {
		"File": "triceCheck.c",
		"Line": 904
	},
	"5630": {
		"File": "triceCheck.c",
		"Line": 645
	},
	"5631": {
		"File": "triceCheck.c",
		"Line": 794
	},
	"5645": {
		"File": "triceCheck.c",
		"Line": 547
	},
	"5650": {
		"File": "triceCheck.c",
		"Line": 1185
	},
	"5654": {
		"File": "triceCheck.c",
		"Line": 871
	},
	"5664": {
		"File": "triceCheck.c",
		"Line": 137
	},
	"5666": {
		"File": "triceCheck.c",
		"Line": 802
	},
	"5668": {
		"File": "triceCheck.c",
		"Line": 795
	},
	"5671": {
		"File": "triceCheck.c",
		"Line": 425
	},
	"5675": {
		"File": "triceCheck.c",
		"Line": 1542
	},
	"5677": {
		"File": "triceCheck.c",
		"Line": 1482
	},
	"5682": {
		"File": "triceCheck.c",
		"Line": 1555
	},
	"5685": {
		"File": "triceCheck.c",
		"Line": 135
	},
	"5686": {
		"File": "triceCheck.c",
		"Line": 825
	},
	"5694": {
		"File": "triceCheck.c",
		"Line": 1153
	},
	"5703": {
		"File": "triceCheck.c",
		"Line": 640
	},
	"5715": {
		"File": "triceCheck.c",
		"Line": 982
	},
	"5720": {
		"File": "triceCheck.c",
		"Line": 466
	},
	"5744": {
		"File": "triceCheck.c",
		"Line": 181
	},
	"5750": {
		"File": "triceCheck.c",
		"Line": 831
	},
	"5755": {
		"File": "triceCheck.c",
		"Line": 859
	},
	"5760": {
		"File": "triceCheck.c",
		"Line": 530
	},
	"5763": {
		"File": "triceCheck.c",
		"Line": 1021
	},
	"5771": {
		"File": "triceCheck.c",
		"Line": 184
	},
	"5777": {
		"File": "triceCheck.c",
		"Line": 739
	},
	"5785": {
		"File": "triceCheck.c",
		"Line": 810
	},
	"5791": {
		"File": "triceCheck.c",
		"Line": 445
	},
	"5793": {
		"File": "triceCheck.c",
		"Line": 1303
	},
	"5819": {
		"File": "triceCheck.c",
		"Line": 397
	},
	"5820": {
		"File": "triceCheck.c",
		"Line": 641
	},
	"5837": {
		"File": "triceCheck.c",
		"Line": 260
	},
	"5853": {
		"File": "triceCheck.c",
		"Line": 606
	},
	"5875": {
		"File": "triceCheck.c",
		"Line": 1240
	},
	"5879": {
		"File": "triceCheck.c",
		"Line": 142
	},
	"5884": {
		"File": "triceCheck.c",
		"Line": 174
	},
	"5892": {
		"File": "triceCheck.c",
		"Line": 471
	},
	"5893": {
		"File": "triceCheck.c",
		"Line": 582
	},
	"5899": {
		"File": "triceCheck.c",
		"Line": 234
	},
	"5902": {
		"File": "triceCheck.c",
		"Line": 1046
	},
	"5909": {
		"File": "triceCheck.c",
		"Line": 933
	},
	"5910": {
		"File": "triceCheck.c",
		"Line": 991
	},
	"5913": {
		"File": "triceCheck.c",
		"Line": 60
	},
	"5918": {
		"File": "triceCheck.c",
		"Line": 365
	},
	"5924": {
		"File": "triceCheck.c",
		"Line": 1117
	},
	"5929": {
		"File": "triceCheck.c",
		"Line": 757
	},
	"5955": {
		"File": "triceCheck.c",
		"Line": 1097
	},
	"5956": {
		"File": "triceCheck.c",
		"Line": 1131
	},
	"5958": {
		"File": "triceCheck.c",
		"Line": 1341
	},
	"5960": {
		"File": "triceCheck.c",
		"Line": 456
	},
	"5968": {
		"File": "triceCheck.c",
		"Line": 512
	},
	"5999": {
		"File": "triceCheck.c",
		"Line": 1217
	},
	"6015": {
		"File": "triceCheck.c",
		"Line": 939
	},
	"6020": {
		"File": "triceCheck.c",
		"Line": 411
	},
	"6033": {
		"File": "triceCheck.c",
		"Line": 890
	},
	"6034": {
		"File": "triceCheck.c",
		"Line": 992
	},
	"6037": {
		"File": "triceCheck.c",
		"Line": 461
	},
	"6048": {
		"File": "triceCheck.c",
		"Line": 965
	},
	"6067": {
		"File": "triceCheck.c",
		"Line": 1314
	},
	"6069": {
		"File": "triceCheck.c",
		"Line": 1337
	},
	"6074": {
		"File": "triceCheck.c",
		"Line": 1181
	},
	"6079": {
		"File": "triceCheck.c",
		"Line": 1210
	},
	"6080": {
		"File": "triceCheck.c",
		"Line": 1071
	},
	"6085": {
		"File": "triceCheck.c",
		"Line": 737
	},
	"6090": {
		"File": "triceCheck.c",
		"Line": 1526
	},
	"6101": {
		"File": "triceCheck.c",
		"Line": 1049
	},
	"6112": {
		"File": "triceCheck.c",
		"Line": 1030
	},
	"6114": {
		"File": "triceCheck.c",
		"Line": 477
	},
	"6118": {
		"File": "triceCheck.c",
		"Line": 1142
	},
	"6121": {
		"File": "triceCheck.c",
		"Line": 529
	},
	"6122": {
		"File": "triceCheck.c",
		"Line": 1120
	},
	"6123": {
		"File": "triceCheck.c",
		"Line": 1074
	},
	"6124": {
		"File": "triceCheck.c",
		"Line": 773
	},
	"6146": {
		"File": "triceCheck.c",
		"Line": 655
	},
	"6147": {
		"File": "triceCheck.c",
		"Line": 276
	},
	"6153": {
		"File": "triceCheck.c",
		"Line": 1249
	},
	"6154": {
		"File": "triceCheck.c",
		"Line": 204
	},
	"6160": {
		"File": "triceCheck.c",
		"Line": 642
	},
	"6167": {
		"File": "triceCheck.c",
		"Line": 1070
	},
	"6170": {
		"File": "triceCheck.c",
		"Line": 1022
	},
	"6210": {
		"File": "triceCheck.c",
		"Line": 517
	},
	"6228": {
		"File": "triceCheck.c",
		"Line": 454
	},
	"6232": {
		"File": "triceCheck.c",
		"Line": 475
	},
	"6233": {
		"File": "triceCheck.c",
		"Line": 870
	},
	"6235": {
		"File": "triceCheck.c",
		"Line": 1145
	},
	"6244": {
		"File": "triceCheck.c",
		"Line": 1285
	},
	"6246": {
		"File": "triceCheck.c",
		"Line": 243
	},
	"6252": {
		"File": "triceCheck.c",
		"Line": 853
	},
	"6254": {
		"File": "triceCheck.c",
		"Line": 1052
	},
	"6257": {
		"File": "triceCheck.c",
		"Line": 1196
	},
	"6258": {
		"File": "triceCheck.c",
		"Line": 524
	},
	"6268": {
		"File": "triceCheck.c",
		"Line": 141
	},
	"6272": {
		"File": "triceCheck.c",
		"Line": 1104
	},
	"6274": {
		"File": "triceCheck.c",
		"Line": 1132
	},
	"6277": {
		"File": "triceCheck.c",
		"Line": 1250
	},
	"6279": {
		"File": "triceCheck.c",
		"Line": 1108
	},
	"6284": {
		"File": "triceCheck.c",
		"Line": 891
	},
	"6305": {
		"File": "triceCheck.c",
		"Line": 901
	},
	"6306": {
		"File": "triceCheck.c",
		"Line": 273
	},
	"6313": {
		"File": "triceCheck.c",
		"Line": 680
	},
	"6322": {
		"File": "triceCheck.c",
		"Line": 396
	},
	"6326": {
		"File": "triceCheck.c",
		"Line": 940
	},
	"6328": {
		"File": "triceCheck.c",
		"Line": 252
	},
	"6335": {
		"File": "triceCheck.c",
		"Line": 967
	},
	"6349": {
		"File": "triceCheck.c",
		"Line": 1090
	},
	"6350": {
		"File": "triceCheck.c",
		"Line": 634
	},
	"6357": {
		"File": "triceCheck.c",
		"Line": 770
	},
	"6363": {
		"File": "triceCheck.c",
		"Line": 1333
	},
	"6367": {
		"File": "triceCheck.c",
		"Line": 1228
	},
	"6380": {
		"File": "triceCheck.c",
		"Line": 131
	},
	"6381": {
		"File": "triceCheck.c",
		"Line": 539
	},
	"6383": {
		"File": "triceCheck.c",
		"Line": 1100
	},
	"6429": {
		"File": "triceCheck.c",
		"Line": 1308
	},
	"6450": {
		"File": "triceCheck.c",
		"Line": 772
	},
	"6454": {
		"File": "triceCheck.c",
		"Line": 993
	},
	"6466": {
		"File": "triceCheck.c",
		"Line": 990
	},
	"6472": {
		"File": "triceCheck.c",
		"Line": 495
	},
	"6474": {
		"File": "triceCheck.c",
		"Line": 144
	},
	"6492": {
		"File": "triceCheck.c",
		"Line": 856
	},
	"6501": {
		"File": "triceCheck.c",
		"Line": 246
	},
	"6505": {
		"File": "triceCheck.c",
		"Line": 805
	},
	"6508": {
		"File": "triceCheck.c",
		"Line": 744
	},
	"6515": {
		"File": "triceCheck.c",
		"Line": 210
	},
	"6521": {
		"File": "triceCheck.c",
		"Line": 834
	},
	"6526": {
		"File": "triceCheck.c",
		"Line": 447
	},
	"6556": {
		"File": "triceCheck.c",
		"Line": 469
	},
	"6558": {
		"File": "triceCheck.c",
		"Line": 1229
	},
	"6559": {
		"File": "triceCheck.c",
		"Line": 1106
	},
	"6561": {
		"File": "triceCheck.c",
		"Line": 399
	},
	"6567": {
		"File": "triceCheck.c",
		"Line": 899
	},
	"6573": {
		"File": "triceCheck.c",
		"Line": 1042
	},
	"6585": {
		"File": "triceCheck.c",
		"Line": 1007
	},
	"6599": {
		"File": "triceCheck.c",
		"Line": 803
	},
	"6605": {
		"File": "triceCheck.c",
		"Line": 441
	},
	"6616": {
		"File": "triceCheck.c",
		"Line": 880
	},
	"6617": {
		"File": "triceCheck.c",
		"Line": 1128
	},
	"6626": {
		"File": "main.c",
		"Line": 94
	},
	"6635": {
		"File": "triceCheck.c",
		"Line": 564
	},
	"6636": {
		"File": "triceCheck.c",
		"Line": 478
	},
	"6641": {
		"File": "triceCheck.c",
		"Line": 468
	},
	"6646": {
		"File": "stm32l4xx_it.c",
		"Line": 206
	},
	"6648": {
		"File": "triceCheck.c",
		"Line": 952
	},
	"6658": {
		"File": "main.c",
		"Line": 93
	},
	"6665": {
		"File": "triceCheck.c",
		"Line": 132
	},
	"6669": {
		"File": "triceCheck.c",
		"Line": 671
	},
	"6677": {
		"File": "triceCheck.c",
		"Line": 1252
	},
	"6689": {
		"File": "triceCheck.c",
		"Line": 1236
	},
	"6692": {
		"File": "triceCheck.c",
		"Line": 669
	},
	"6696": {
		"File": "triceCheck.c",
		"Line": 607
	},
	"6701": {
		"File": "triceCheck.c",
		"Line": 662
	},
	"6721": {
		"File": "triceCheck.c",
		"Line": 1552
	},
	"6724": {
		"File": "triceCheck.c",
		"Line": 1144
	},
	"6739": {
		"File": "triceCheck.c",
		"Line": 985
	},
	"6743": {
		"File": "triceCheck.c",
		"Line": 755
	},
	"6750": {
		"File": "triceCheck.c",
		"Line": 497
	},
	"6751": {
		"File": "triceCheck.c",
		"Line": 1003
	},
	"6761": {
		"File": "triceCheck.c",
		"Line": 242
	},
	"6763": {
		"File": "triceCheck.c",
		"Line": 964
	},
	"6764": {
		"File": "triceCheck.c",
		"Line": 961
	},
	"6772": {
		"File": "triceCheck.c",
		"Line": 1263
	},
	"6773": {
		"File": "triceCheck.c",
		"Line": 1182
	},
	"6780": {
		"File": "triceCheck.c",
		"Line": 531
	},
	"6788": {
		"File": "triceCheck.c",
		"Line": 691
	},
	"6789": {
		"File": "triceCheck.c",
		"Line": 584
	},
	"6798": {
		"File": "triceCheck.c",
		"Line": 1320
	},
	"6801": {
		"File": "triceCheck.c",
		"Line": 1125
	},
	"6802": {
		"File": "triceCheck.c",
		"Line": 749
	},
	"6812": {
		"File": "triceCheck.c",
		"Line": 1179
	},
	"6814": {
		"File": "triceCheck.c",
		"Line": 1061
	},
	"6818": {
		"File": "triceCheck.c",
		"Line": 1221
	},
	"6835": {
		"File": "triceCheck.c",
		"Line": 735
	},
	"6848": {
		"File": "triceCheck.c",
		"Line": 194
	},
	"6851": {
		"File": "triceCheck.c",
		"Line": 1026
	},
	"6882": {
		"File": "triceCheck.c",
		"Line": 1309
	},
	"6885": {
		"File": "triceCheck.c",
		"Line": 568
	},
	"6902": {
		"File": "triceCheck.c",
		"Line": 975
	},
	"6904": {
		"File": "triceCheck.c",
		"Line": 1507
	},
	"6906": {
		"File": "triceCheck.c",
		"Line": 764
	},
	"6909": {
		"File": "triceCheck.c",
		"Line": 280
	},
	"6912": {
		"File": "triceCheck.c",
		"Line": 1158
	},
	"6915": {
		"File": "triceCheck.c",
		"Line": 248
	},
	"6920": {
		"File": "triceCheck.c",
		"Line": 1051
	},
	"6931": {
		"File": "triceCheck.c",
		"Line": 591
	},
	"6934": {
		"File": "triceCheck.c",
		"Line": 1187
	},
	"6938": {
		"File": "main.c",
		"Line": 89
	},
	"6944": {
		"File": "triceCheck.c",
		"Line": 1151
	},
	"6953": {
		"File": "triceCheck.c",
		"Line": 1211
	},
	"6954": {
		"File": "triceCheck.c",
		"Line": 1067
	},
	"6958": {
		"File": "triceCheck.c",
		"Line": 562
	},
	"6960": {
		"File": "triceCheck.c",
		"Line": 649
	},
	"6964": {
		"File": "triceCheck.c",
		"Line": 592
	},
	"6969": {
		"File": "triceCheck.c",
		"Line": 373
	},
	"6979": {
		"File": "triceCheck.c",
		"Line": 1534
	},
	"6981": {
		"File": "triceCheck.c",
		"Line": 1204
	},
	"6990": {
		"File": "triceCheck.c",
		"Line": 1540
	},
	"6991": {
		"File": "triceCheck.c",
		"Line": 969
	},
	"6996": {
		"File": "triceCheck.c",
		"Line": 937
	},
	"6999": {
		"File": "triceCheck.c",
		"Line": 1122
	},
	"7002": {
		"File": "triceCheck.c",
		"Line": 442
	},
	"7031": {
		"File": "triceCheck.c",
		"Line": 1366
	},
	"7033": {
		"File": "triceCheck.c",
		"Line": 740
	},
	"7035": {
		"File": "triceCheck.c",
		"Line": 351
	},
	"7042": {
		"File": "triceCheck.c",
		"Line": 763
	},
	"7047": {
		"File": "triceCheck.c",
		"Line": 868
	},
	"7062": {
		"File": "triceCheck.c",
		"Line": 404
	},
	"7067": {
		"File": "triceCheck.c",
		"Line": 357
	},
	"7073": {
		"File": "triceCheck.c",
		"Line": 747
	},
	"7085": {
		"File": "triceCheck.c",
		"Line": 765
	},
	"7103": {
		"File": "triceCheck.c",
		"Line": 1189
	},
	"7114": {
		"File": "triceCheck.c",
		"Line": 780
	},
	"7119": {
		"File": "triceCheck.c",
		"Line": 958
	},
	"7120": {
		"File": "triceCheck.c",
		"Line": 465
	},
	"7125": {
		"File": "triceCheck.c",
		"Line": 934
	},
	"7131": {
		"File": "triceCheck.c",
		"Line": 781
	},
	"7133": {
		"File": "triceCheck.c",
		"Line": 613
	},
	"7142": {
		"File": "triceCheck.c",
		"Line": 285
	},
	"7162": {
		"File": "triceCheck.c",
		"Line": 767
	},
	"7164": {
		"File": "main.c",
		"Line": 338
	},
	"7170": {
		"File": "triceCheck.c",
		"Line": 518
	},
	"7171": {
		"File": "triceCheck.c",
		"Line": 999
	},
	"7172": {
		"File": "triceCheck.c",
		"Line": 520
	},
	"7185": {
		"File": "triceCheck.c",
		"Line": 981
	},
	"7187": {
		"File": "triceCheck.c",
		"Line": 1296
	},
	"7207": {
		"File": "triceCheck.c",
		"Line": 977
	},
	"7211": {
		"File": "triceCheck.c",
		"Line": 721
	},
	"7214": {
		"File": "triceCheck.c",
		"Line": 779
	},
	"7222": {
		"File": "triceCheck.c",
		"Line": 1044
	},
	"7226": {
		"File": "triceCheck.c",
		"Line": 706
	},
	"7245": {
		"File": "triceCheck.c",
		"Line": 458
	},
	"7246": {
		"File": "triceCheck.c",
		"Line": 1085
	},
	"7249": {
		"File": "triceCheck.c",
		"Line": 1254
	},
	"7252": {
		"File": "triceCheck.c",
		"Line": 1188
	},
	"7253": {
		"File": "triceCheck.c",
		"Line": 1086
	},
	"7255": {
		"File": "triceCheck.c",
		"Line": 672
	},
	"7261": {
		"File": "triceCheck.c",
		"Line": 527
	},
	"7264": {
		"File": "triceCheck.c",
		"Line": 1369
	},
	"7266": {
		"File": "triceCheck.c",
		"Line": 631
	},
	"7276": {
		"File": "triceCheck.c",
		"Line": 262
	},
	"7277": {
		"File": "triceCheck.c",
		"Line": 862
	},
	"7282": {
		"File": "triceCheck.c",
		"Line": 705
	},
	"7290": {
		"File": "triceCheck.c",
		"Line": 1232
	},
	"7296": {
		"File": "triceCheck.c",
		"Line": 656
	},
	"7297": {
		"File": "triceCheck.c",
		"Line": 722
	},
	"7299": {
		"File": "triceCheck.c",
		"Line": 687
	},
	"7300": {
		"File": "triceCheck.c",
		"Line": 910
	},
	"7309": {
		"File": "triceCheck.c",
		"Line": 298
	},
	"7314": {
		"File": "triceCheck.c",
		"Line": 57
	},
	"7320": {
		"File": "triceCheck.c",
		"Line": 850
	},
	"7323": {
		"File": "triceCheck.c",
		"Line": 750
	},
	"7330": {
		"File": "triceCheck.c",
		"Line": 654
	},
	"7345": {
		"File": "triceCheck.c",
		"Line": 673
	},
	"7357": {
		"File": "triceCheck.c",
		"Line": 1190
	},
	"7362": {
		"File": "triceCheck.c",
		"Line": 536
	},
	"7363": {
		"File": "triceCheck.c",
		"Line": 1116
	},
	"7366": {
		"File": "triceCheck.c",
		"Line": 986
	},
	"7378": {
		"File": "triceCheck.c",
		"Line": 643
	},
	"7387": {
		"File": "triceCheck.c",
		"Line": 1174
	},
	"7388": {
		"File": "triceCheck.c",
		"Line": 882
	},
	"7392": {
		"File": "triceCheck.c",
		"Line": 50
	},
	"7406": {
		"File": "triceCheck.c",
		"Line": 1226
	},
	"7413": {
		"File": "triceCheck.c",
		"Line": 360
	},
	"7415": {
		"File": "triceCheck.c",
		"Line": 1009
	},
	"7421": {
		"File": "triceCheck.c",
		"Line": 1244
	},
	"7434": {
		"File": "triceCheck.c",
		"Line": 537
	},
	"7435": {
		"File": "triceCheck.c",
		"Line": 931
	},
	"7437": {
		"File": "triceCheck.c",
		"Line": 793
	},
	"7461": {
		"File": "triceCheck.c",
		"Line": 173
	},
	"7464": {
		"File": "triceCheck.c",
		"Line": 1136
	},
	"7465": {
		"File": "triceCheck.c",
		"Line": 935
	},
	"7476": {
		"File": "main.c",
		"Line": 87
	},
	"7479": {
		"File": "triceCheck.c",
		"Line": 867
	},
	"7483": {
		"File": "triceCheck.c",
		"Line": 778
	},
	"7489": {
		"File": "triceCheck.c",
		"Line": 925
	},
	"7495": {
		"File": "triceCheck.c",
		"Line": 819
	},
	"7496": {
		"File": "triceCheck.c",
		"Line": 1102
	},
	"7501": {
		"File": "triceCheck.c",
		"Line": 410
	},
	"7502": {
		"File": "triceCheck.c",
		"Line": 366
	},
	"7516": {
		"File": "triceCheck.c",
		"Line": 728
	},
	"7520": {
		"File": "triceCheck.c",
		"Line": 593
	},
	"7524": {
		"File": "triceCheck.c",
		"Line": 983
	},
	"7526": {
		"File": "triceCheck.c",
		"Line": 922
	},
	"7527": {
		"File": "triceCheck.c",
		"Line": 1173
	},
	"7528": {
		"File": "triceCheck.c",
		"Line": 782
	},
	"7532": {
		"File": "triceCheck.c",
		"Line": 1214
	},
	"7536": {
		"File": "triceCheck.c",
		"Line": 909
	},
	"7541": {
		"File": "triceCheck.c",
		"Line": 457
	},
	"7547": {
		"File": "triceCheck.c",
		"Line": 1491
	},
	"7557": {
		"File": "triceCheck.c",
		"Line": 401
	},
	"7563": {
		"File": "triceCheck.c",
		"Line": 1310
	},
	"7565": {
		"File": "triceCheck.c",
		"Line": 1233
	},
	"7568": {
		"File": "triceCheck.c",
		"Line": 974
	},
	"7570": {
		"File": "triceCheck.c",
		"Line": 884
	},
	"7575": {
		"File": "triceCheck.c",
		"Line": 814
	},
	"7576": {
		"File": "triceCheck.c",
		"Line": 646
	},
	"7578": {
		"File": "triceCheck.c",
		"Line": 1319
	},
	"7594": {
		"File": "triceCheck.c",
		"Line": 426
	},
	"7617": {
		"File": "triceCheck.c",
		"Line": 362
	},
	"7625": {
		"File": "triceCheck.c",
		"Line": 424
	},
	"7627": {
		"File": "triceCheck.c",
		"Line": 196
	},
	"7630": {
		"File": "triceCheck.c",
		"Line": 1260
	},
	"7647": {
		"File": "triceCheck.c",
		"Line": 1329
	},
	"7654": {
		"File": "triceCheck.c",
		"Line": 1208
	},
	"7655": {
		"File": "triceCheck.c",
		"Line": 622
	},
	"7666": {
		"File": "triceCheck.c",
		"Line": 647
	},
	"7669": {
		"File": "triceCheck.c",
		"Line": 1014
	},
	"7672": {
		"File": "triceCheck.c",
		"Line": 1323
	},
	"7675": {
		"File": "triceCheck.c",
		"Line": 998
	},
	"7713": {
		"File": "triceCheck.c",
		"Line": 385
	},
	"7717": {
		"File": "triceCheck.c",
		"Line": 602
	},
	"7728": {
		"File": "triceCheck.c",
		"Line": 1156
	},
	"7741": {
		"File": "triceCheck.c",
		"Line": 1492
	},
	"7743": {
		"File": "triceCheck.c",
		"Line": 1147
	},
	"7749": {
		"File": "triceCheck.c",
		"Line": 1058
	},
	"7756": {
		"File": "triceCheck.c",
		"Line": 703
	},
	"7759": {
		"File": "triceCheck.c",
		"Line": 1087
	},
	"7769": {
		"File": "triceCheck.c",
		"Line": 830
	},
	"7785": {
		"File": "triceCheck.c",
		"Line": 1063
	},
	"7788": {
		"File": "triceCheck.c",
		"Line": 479
	},
	"7789": {
		"File": "triceCheck.c",
		"Line": 1083
	},
	"7793": {
		"File": "triceCheck.c",
		"Line": 266
	},
	"7799": {
		"File": "triceCheck.c",
		"Line": 857
	},
	"7805": {
		"File": "triceCheck.c",
		"Line": 55
	},
	"7806": {
		"File": "triceCheck.c",
		"Line": 310
	},
	"7810": {
		"File": "triceCheck.c",
		"Line": 681
	},
	"7815": {
		"File": "triceCheck.c",
		"Line": 1152
	},
	"7816": {
		"File": "triceCheck.c",
		"Line": 473
	},
	"7822": {
		"File": "triceCheck.c",
		"Line": 525
	},
	"7825": {
		"File": "triceCheck.c",
		"Line": 191
	},
	"7834": {
		"File": "triceCheck.c",
		"Line": 382
	},
	"7836": {
		"File": "triceCheck.c",
		"Line": 851
	},
	"7837": {
		"File": "triceCheck.c",
		"Line": 576
	},
	"7847": {
		"File": "triceCheck.c",
		"Line": 1114
	},
	"7851": {
		"File": "triceCheck.c",
		"Line": 1041
	},
	"7862": {
		"File": "triceCheck.c",
		"Line": 171
	},
	"7864": {
		"File": "triceCheck.c",
		"Line": 800
	},
	"7873": {
		"File": "triceCheck.c",
		"Line": 1238
	},
	"7881": {
		"File": "triceCheck.c",
		"Line": 666
	},
	"7882": {
		"File": "triceCheck.c",
		"Line": 1135
	},
	"7888": {
		"File": "triceCheck.c",
		"Line": 759
	},
	"7904": {
		"File": "triceCheck.c",
		"Line": 1328
	},
	"7915": {
		"File": "triceCheck.c",
		"Line": 752
	},
	"7919": {
		"File": "triceCheck.c",
		"Line": 1203
	},
	"7921": {
		"File": "triceCheck.c",
		"Line": 1176
	},
	"7922": {
		"File": "triceCheck.c",
		"Line": 1336
	},
	"7930": {
		"File": "triceCheck.c",
		"Line": 186
	},
	"7941": {
		"File": "triceCheck.c",
		"Line": 275
	},
	"7943": {
		"File": "triceCheck.c",
		"Line": 1035
	},
	"7944": {
		"File": "triceCheck.c",
		"Line": 221
	},
	"7945": {
		"File": "triceCheck.c",
		"Line": 1001
	},
	"7948": {
		"File": "triceCheck.c",
		"Line": 374
	},
	"7949": {
		"File": "triceCheck.c",
		"Line": 504
	},
	"7960": {
		"File": "triceCheck.c",
		"Line": 827
	},
	"7971": {
		"File": "triceCheck.c",
		"Line": 1496
	},
	"7977": {
		"File": "triceCheck.c",
		"Line": 1109
	},
	"7985": {
		"File": "triceCheck.c",
		"Line": 1094
	},
	"7989": {
		"File": "triceCheck.c",
		"Line": 1259
	},
	"7992": {
		"File": "triceCheck.c",
		"Line": 936
	},
	"7994": {
		"File": "triceCheck.c",
		"Line": 1304
	}
}